drove.py
drovecli.py
droveclient.py
droveutils.py
plugins/__init__.py
plugins/appinstances.py
plugins/applications.py
plugins/cluster.py
plugins/config.py
plugins/describe.py
plugins/executors.py
plugins/localserviceinstances.py
plugins/localservices.py
plugins/tasks.py
drove_cli-0.0.10.dist-info/METADATA
drove_cli-0.0.10.dist-info/WHEEL
drove_cli-0.0.10.dist-info/entry_points.txt
drove_cli-0.0.10.dist-info/RECORD
