Metadata-Version: 2.4
Name: drove-cli
Version: 0.0.10
Summary: Drove Command Line Interface
License: Apache-2.0
Keywords: container,docker,podman,distributed-systems,container-orchestrator
Author: Santanu Sinha
Author-email: santanu.sinha@gmail.com
Maintainer: Santanu Sinha
Maintainer-email: santanu.sinha@gmail.com
Requires-Python: >=3.9,<4.0
Classifier: Development Status :: 5 - Production/Stable
Classifier: Intended Audience :: Developers
Classifier: Intended Audience :: System Administrators
Classifier: License :: OSI Approved :: Apache Software License
Classifier: Programming Language :: Python :: 3
Classifier: Programming Language :: Python :: 3.9
Classifier: Programming Language :: Python :: 3.10
Classifier: Programming Language :: Python :: 3.11
Classifier: Programming Language :: Python :: 3.12
Classifier: Programming Language :: Python :: 3.13
Classifier: Programming Language :: Python :: 3.14
Classifier: Topic :: System :: Clustering
Classifier: Topic :: System :: Distributed Computing
Requires-Dist: requests (>=2.31.0,<3.0.0)
Requires-Dist: shtab (==1.8.0)
Requires-Dist: tabulate (>=0.9.0,<0.10.0)
Requires-Dist: tenacity (>=8.2.3,<9.0.0)
Requires-Dist: urllib3 (>=2.0.7,<3.0.0)
Project-URL: Repository, https://github.com/PhonePe/drove-cli
